APB_memory.srcs/sources_1/new/APB_mem.v
`timescale 1ns / 1ps

module APB_mem(Pclk, Prst,Paddr, Pselx,Penable, Pwrite, Pwdata, Pready, Pslverr, Prdata, temp);

input Pclk;
input Prst;
input [5:0] Paddr;
input Pselx;
input Penable;
input Pwrite;
input [31:0] Pwdata;

output reg Pready;
output reg Pslverr;
output reg [31:0] Prdata;
output reg [31:0] temp;

reg [31:0] mem[31:0];
parameter [1:0] idle =2'b00; 
parameter [1:0]setup = 2'b01;
parameter [1:0] access=2'b10;

reg [1:0] present_state, next_state;

always@(posedge Pclk or negedge Prst)//asynchronous
begin
if(Prst ==0) begin//active low
present_state <= idle;
//next_state <= present_state;
end
else 
present_state <= next_state;
end

always @(*) begin
next_state = present_state;

case(present_state)

idle:begin
    //if(Pselx & !Penable)
    next_state = setup;
    end
setup:begin
    if( Pselx) begin
    //Pready = 1;
    next_state = access;
    end
    else
    next_state = idle;
    end
    
access: begin
    Pready = 1;
    if(Penable & Pwrite)
    begin
        if(Paddr>31) Pslverr =1;
        else begin
            mem[Paddr] = Pwdata;
            temp = mem[Paddr];
    
            Pslverr = 0;
             end
    end
    else if (Penable & Pwrite ==0) begin
    Prdata = mem[Paddr];
   // temp =mem[Paddr];
    
    //Pslverr = 0;
        end
        
     if(!Penable) begin
     next_state = setup;
     //Pready = 0;
     end
     end
endcase 
end

endmodule

APB_memory.srcs/sim_1/new/tb.v
`timescale 1ns / 1ps
module tb();
reg Pclk;
reg Prst;
reg [5:0] Paddr;
reg Pselx;
reg Penable;
reg Pwrite;
reg [31:0] Pwdata;

wire  Pready;
wire Pslverr;
wire [31:0] Prdata;
wire [31:0] temp;

APB_mem dut(Pclk, Prst,Paddr, Pselx,Penable, Pwrite, Pwdata, Pready, Pslverr, Prdata, temp);

initial Pclk =1;
always #10 Pclk =~Pclk;

task reset_and_initialization;
begin
#5 Prst =0;
@(posedge Pclk);

Prst=1;
Pselx=1'b0;
Penable = 1'bx;
Pwrite = 1'bx;
Paddr = 6'bx;
end
endtask


task write_transfer;
begin
Pselx=1;
Pwrite=1;
Pwdata=$random;
Paddr = $random;
//#10;
@(posedge Pclk);
Penable =1;
//wait (Pready == 1) begin
//Pselx =Pselx;
//Pwrite = Pwrite;
//Penable = Penable;
//Paddr = Paddr;
//Pwdata = Pwdata;
//end
@(posedge Pclk);
Penable = 0;

$strobe ("writong data into memory data =%0d, address =%0d" , Pwdata, Paddr);

end
endtask

task read_transfer;
begin
Pselx =1;
Pwrite = 0;
@(posedge Pclk);
Penable=1;

//wait (Pready ==1) begin
//Pselx =Pselx;
//Pwrite = Pwrite;
//Penable = Penable;
//Paddr = Paddr;
//Pwdata = Pwdata; end

@(posedge Pclk);
Penable = 0;
Pselx =0;

$strobe("reading data from memory data =%0d, address =%0d", Prdata, Paddr);
end
endtask


task read_write_transfer;
begin
@(posedge Pclk);
repeat(3)
begin
write_transfer;
read_transfer;

end
end
endtask

initial begin

reset_and_initialization;
read_write_transfer;

#80; $finish;
end

initial begin
$dumpfile("dump.vcd");
$dumpvars;
 
end

endmodule

APB_memory.sim/sim_1/behav/xsim/dump.vcd
$date
   Wed Mar 12 13:47:30 2025
$end

$version
  2024.2.0
  $dumpfile ("dump.vcd") 
$end

$timescale
  1ps
$end

$scope module tb $end
$var reg 1 ! Pclk $end
$var reg 1 " Prst $end
$var reg 6 # Paddr [5:0] $end
$var reg 1 $ Pselx $end
$var reg 1 % Penable $end
$var reg 1 & Pwrite $end
$var reg 32 ' Pwdata [31:0] $end
$var wire 1 ( Pready $end
$var wire 1 ) Pslverr $end
$var wire 32 * Prdata [31:0] $end
$var wire 32 + temp [31:0] $end
$scope module dut $end
$var wire 1 , Pclk $end
$var wire 1 - Prst $end
$var wire 6 . Paddr [5:0] $end
$var wire 1 / Pselx $end
$var wire 1 0 Penable $end
$var wire 1 1 Pwrite $end
$var wire 32 2 Pwdata [31:0] $end
$var reg 1 3 Pready $end
$var reg 1 4 Pslverr $end
$var reg 32 5 Prdata [31:0] $end
$var reg 32 6 temp [31:0] $end
$var reg 2 7 present_state [1:0] $end
$var reg 2 8 next_state [1:0] $end
$upscope $end
$scope task reset_and_initialization $end
$upscope $end
$scope task write_transfer $end
$upscope $end
$scope task read_transfer $end
$upscope $end
$scope task read_write_transfer $end
$upscope $end
$upscope $end
$enddefinitions $end

#0
$dumpvars
1!
x"
bx #
x$
x%
x&
bx '
x(
x)
bx *
bx +
1,
x-
bx .
x/
x0
x1
bx 2
x3
x4
bx 5
bx 6
bx 7
bx 8
$end

#5000
0"
0-
b0 7
b1 8

#10000
0!
0,

#20000
1!
1"
0$
1,
1-
0/
b1 7
b0 8

#30000
0!
0,

#40000
1!
b1 #
1$
1&
b10010000101010011010100100100 '
1,
b1 .
1/
11
b10010000101010011010100100100 2
b0 7
b1 8

#50000
0!
0,

#60000
1!
1%
1,
10
b1 7
b10 8

#70000
0!
0,

#80000
1!
0%
0&
1(
1,
00
01
13
b10 7
b1 8

#90000
0!
0,

#100000
1!
1%
1,
10
b1 7
b10 8

#110000
0!
0,

#120000
1!
b100011 #
1$
0%
1&
b10000100100001001101011000001001 '
1,
b100011 .
00
11
b10000100100001001101011000001001 2
b10 7
b1 8

#130000
0!
0,

#140000
1!
1%
1)
1,
10
14
b1 7
b10 8

#150000
0!
0,

#160000
1!
0%
0&
1,
00
01
b10 7
b1 8

#170000
0!
0,

#180000
1!
1%
1,
10
b1 7
b10 8

#190000
0!
0,

#200000
1!
b1101 #
1$
0%
1&
b110101110010111101100001101 '
1,
b1101 .
00
11
b110101110010111101100001101 2
b10 7
b1 8

#210000
0!
0,

#220000
1!
1%
0)
b110101110010111101100001101 +
1,
10
04
b110101110010111101100001101 6
b1 7
b10 8

#230000
0!
0,

#240000
1!
0%
0&
1,
00
01
b10 7
b1 8

#250000
0!
0,

#260000
1!
1%
b110101110010111101100001101 *
1,
10
b110101110010111101100001101 5
b1 7
b10 8

#270000
0!
0,

#280000
1!
0$
0%
1,
0/
00
b10 7
b1 8

#290000
0!
0,

#300000
1!
1,
b1 7
b0 8

#310000
0!
0,

#320000
1!
1,
b0 7
b1 8

#330000
0!
0,

#340000
1!
1,
b1 7
b0 8

